spotdownloader/SpotDownloader.py
spotdownloader/__init__.py
spotdownloader/__main__.py
spotdownloader/audio_metadata.py
spotdownloader/os_helper.py
spotdownloader/tagdemo.py
SpotDownloader-1.0.5.dist-info/LICENSE.txt
SpotDownloader-1.0.5.dist-info/METADATA
SpotDownloader-1.0.5.dist-info/WHEEL
SpotDownloader-1.0.5.dist-info/entry_points.txt
SpotDownloader-1.0.5.dist-info/top_level.txt
SpotDownloader-1.0.5.dist-info/RECORD
