Metadata-Version: 2.1
Name: SpotDownloader
Version: 1.0.5
Summary: This is a simple and easy to use app made in python that downloads all you music in .MP3 from a given spotify playlist, even your private ones!
Home-page: https://github.com/elblogbruno/SpotDownloader
Author: Bruno Moya
Author-email: me@brunomoya.com
License: MIT
Keywords: songs lyrics spotify download youtube
Platform: UNKNOWN
Classifier: Topic :: Software Development :: Libraries
Classifier: Operating System :: OS Independent
Classifier: License :: OSI Approved :: MIT License
Classifier: Programming Language :: Python
Classifier: Programming Language :: Python :: 3
Requires-Dist: youtube-dl
Requires-Dist: spotipy
Requires-Dist: pyfiglet
